tclogger/__init__.py
tclogger/args.py
tclogger/attrs.py
tclogger/bars.py
tclogger/colors.py
tclogger/confirms.py
tclogger/copies.py
tclogger/cursors.py
tclogger/decorations.py
tclogger/dicts.py
tclogger/envs.py
tclogger/exceptions.py
tclogger/files.py
tclogger/fills.py
tclogger/formats.py
tclogger/jsons.py
tclogger/logs.py
tclogger/matches.py
tclogger/maths.py
tclogger/params.py
tclogger/paths.py
tclogger/renames.py
tclogger/runtimes.py
tclogger/strings.py
tclogger/tables.py
tclogger/times.py
tclogger/tmux.py
tclogger/trees.py
tclogger/types.py
tclogger-1.11.1.2.dist-info/licenses/LICENSE
tclogger-1.11.1.2.dist-info/METADATA
tclogger-1.11.1.2.dist-info/WHEEL
tclogger-1.11.1.2.dist-info/entry_points.txt
tclogger-1.11.1.2.dist-info/top_level.txt
tclogger-1.11.1.2.dist-info/RECORD
