Metadata-Version: 2.4
Name: tclogger
Version: 1.11.1.2
Summary: Python terminal colored logger
Author: Hansimov
License-Expression: MIT
Project-URL: Homepage, https://github.com/Hansimov/tclogger
Project-URL: Issues, https://github.com/Hansimov/tclogger/issues
Classifier: Programming Language :: Python :: 3
Classifier: Operating System :: OS Independent
Requires-Python: >=3.6
License-File: LICENSE
Requires-Dist: tzdata
Requires-Dist: rapidfuzz
Provides-Extra: all
Requires-Dist: tzdata; extra == "all"
Requires-Dist: rapidfuzz; extra == "all"
Dynamic: license-file
